{
  "url": "https://smart-lab.ru/blog/1147633.php?nomobile=1",
  "article_id": 1147633,
  "title": "Лучшие системы и индикаторы 2001–2005: подборка из архива классического издания по теханализу",
  "comments": [
    {
      "id": 18193359,
      "author": "Михаил Шардин",
      "datetime": "2025-05-08T15:54:00.000Z",
      "text": "Опубликовал вторую часть подборки лучших систем и индикаторов (2006-2010) из легендарного журнала Technical Analysis of STOCKS & COMMODITIES.smart-lab.ru/blog/1151012.php?nomobile=1"
    },
    {
      "id": 18160993,
      "author": "Клетчатый",
      "datetime": "2025-04-29T04:41:00.000Z",
      "text": "да ужж, было время лет 10 назад, скачивал я его. Но на этом все и заканчивалось"
    },
    {
      "id": 18160994,
      "author": "Михаил Шардин",
      "datetime": "2025-04-29T04:48:00.000Z",
      "text": "Клетчатый, некоторые идеи мне кажется можно взять"
    },
    {
      "id": 18160998,
      "author": "chizhan",
      "datetime": "2025-04-29T05:03:00.000Z",
      "text": "Одни обложки журналов уже суперские"
    },
    {
      "id": 18161000,
      "author": "Михаил Шардин",
      "datetime": "2025-04-29T05:05:00.000Z",
      "text": "chizhan, крутые"
    },
    {
      "id": 18160999,
      "author": "Михаил Шардин",
      "datetime": "2025-04-29T05:04:00.000Z",
      "text": "В старом и новом дизайне Смартлаба оформление статьи почему-то совершенно по разному считывается...В старом дизайне корректнее отображается:https://smart-lab.ru/blog/1147633.php?nomobile=1"
    },
    {
      "id": 18161356,
      "author": "SergeyJu",
      "datetime": "2025-04-29T09:06:00.000Z",
      "text": "Если дойдут руки, попробую что-нибудь проверить. Навскидку, мало оригинального, в основном вариации давно знакомого."
    },
    {
      "id": 18161386,
      "author": "Михаил Шардин",
      "datetime": "2025-04-29T09:14:00.000Z",
      "text": "SergeyJu, 2001 год"
    },
    {
      "id": 18161375,
      "author": "Тимофей Мартынов",
      "datetime": "2025-04-29T09:11:00.000Z",
      "text": "Ну блин, так много материала"
    },
    {
      "id": 18161383,
      "author": "Михаил Шардин",
      "datetime": "2025-04-29T09:13:00.000Z",
      "text": "Тимофей Мартынов, решил по 5 лет разбить, но всё равно большой объем получился"
    },
    {
      "id": 18161522,
      "author": "Скуфыч",
      "datetime": "2025-04-29T09:52:00.000Z",
      "text": "Эти книги пример того как можно зарабатывать на фонде успешно! Достаточно просто продавать эти книги))"
    },
    {
      "id": 18161786,
      "author": "Михаил Шардин",
      "datetime": "2025-04-29T10:51:00.000Z",
      "text": "Скуфыч, а про какие книги речь?"
    },
    {
      "id": 18161731,
      "author": "Просто трейдер",
      "datetime": "2025-04-29T10:40:00.000Z",
      "text": "Вот это реально полезная статья!"
    },
    {
      "id": 18161787,
      "author": "Михаил Шардин",
      "datetime": "2025-04-29T10:51:00.000Z",
      "text": "Просто трейдер, подборка"
    },
    {
      "id": 18161752,
      "author": "Маркиз Лафайет",
      "datetime": "2025-04-29T10:44:00.000Z",
      "text": "Офигеть, миллениум  уже был четверть века назад."
    },
    {
      "id": 18161788,
      "author": "Михаил Шардин",
      "datetime": "2025-04-29T10:51:00.000Z",
      "text": "Маркиз Лафайет, ага, моложе не становимся"
    },
    {
      "id": 18161812,
      "author": "Михаил Шардин",
      "datetime": "2025-04-29T10:57:00.000Z",
      "text": "Сергей Сергаев, как но только найти эти алмазы и граали?"
    },
    {
      "id": 18162119,
      "author": "Михаил Шардин",
      "datetime": "2025-04-29T12:01:00.000Z",
      "text": "Сергей Сергаев, Money management?"
    },
    {
      "id": 18162256,
      "author": "svgr",
      "datetime": "2025-04-29T12:37:00.000Z",
      "text": "Михаил Шардин, принципиально не различаются. На графиках цены или эквити и т. п. строятся всё равно индикаторы. Просто второе позволяет побарахтаться подольше, слить медленнее."
    },
    {
      "id": 18162299,
      "author": "svgr",
      "datetime": "2025-04-29T12:52:00.000Z",
      "text": "Сергей Сергаев, появляется зависимость прибыльности от длины трейда. Технически как определять, что трейд уже закончен или его ещё нужно продолжать? Граница между 'короткими' и 'длинными' трейдами — новый параметр. чем этот подход лучше поиска какого-то параметра в чудо-индикаторе?"
    },
    {
      "id": 18163377,
      "author": "22022022",
      "datetime": "2025-04-29T17:35:00.000Z",
      "text": "Красивые обложки. Это лишь подборка за 2001г.-2005г. А сколько комбинации можно реализовать… на всё жизнь хватит))"
    }
  ]
}